{
    "Title": "2018 Kia Forte LX Sedan Automatic",
    "Cash Price": "$7,995",
    "Finance Price": "$149/moEstimate",
    "Finance Details": "$800 due at signing \u00b7 72 mo \u00b7 14.22% APR",
    "Exterior": "Deep Sea Blue",
    "Interior": "Black",
    "Mileage": "West Chester, OH (1913 miles away)",
    "Fuel Type": "Gas",
    "MPG": "29 city / 37 highway",
    "Transmission": "Automatic Transmission",
    "Drivetrain": "FWD",
    "Engine": "N/A",
    "Location": "N/A",
    "Listed Since": "Listed 168 days ago",
    "VIN": "3KPFL4A79JE179572",
    "Stock Number": "179572",
    "Features": "Black, Cloth Seat Trim; LX Popular Package; Carpeted Floor Mats; Backup Camera; Bluetooth; 4-Cyl 2.0 Liter; Automatic 6-Spd w/Sportmatic; FWD; Hill Start Assist Control; Traction Control; Electronic Stability Control; ABS (4-Wheel); Keyless Entry; Air Conditioning; Power Windows; Power Door Locks; Cruise Control; Power Steering; Tilt & Telescoping Wheel; AM/FM Stereo; CD/MP3 (Single Disc); SiriusXM Satellite; Bluetooth Wireless; Dual Air Bags; Side Air Bags; F&R Head Curtain Air Bags; See less"
}