{
    "Title": "2022 Chrysler Pacifica Touring L FWD",
    "Cash Price": "$19,347",
    "Finance Price": "$290/moEstimate",
    "Finance Details": "$2,500 due at signing \u00b7 72 mo \u00b7 7.39% APR",
    "Exterior": "Brilliant Black Crystal Pearlcoat",
    "Interior": "Black/Alloy/Black",
    "Mileage": "64,222 miles",
    "Fuel Type": "Gas",
    "MPG": "19 city / 28 highway",
    "Transmission": "Automatic Transmission",
    "Drivetrain": "FWD",
    "Engine": "3.6L V-6 Gas V",
    "Location": "Glenview, IL",
    "Listed Since": "52 days ago",
    "VIN": "2C4RC1BG1NR190211",
    "Stock Number": "P8036",
    "Features": "Engine: 3.6L V6 24V VVT Upg I with Ess; Transmission: 9 Speed 948te Automatic; Quick Order Package 27L; 17\" X 7.0\" Aluminum Wheels; Tires: 235/65R17 BSW As; Safety Sphere Unavailable; Black Seats; Parksense Rear Park Assist Unavailable; See less; Wheel Type; Power Trunk/Liftgate; Apple CarPlay; Android Auto; Seat Material; See all features; Driver Air Bag; Passenger Air Bag; Front Head Air Bag; Rear Head Air Bag; Multi-Zone A/C; See all features"
}