{
    "Title": "2013 Hyundai Sonata GLS 2.4L",
    "Cash Price": "$7,041",
    "Finance Price": "Not Available",
    "Finance Details": "Not Available",
    "Exterior": "Pacific Blue Pearl",
    "Interior": "Gray",
    "Mileage": "98,419 miles",
    "Fuel Type": "Gas",
    "MPG": "24 city / 35 highway",
    "Transmission": "Automatic Transmission",
    "Drivetrain": "FWD",
    "Engine": "2.4L Inline-4 Gas Inline",
    "Location": "Pensacola, FL",
    "Listed Since": "96 days ago",
    "VIN": "5NPEB4ACXDH780940",
    "Stock Number": "780940",
    "Features": ""
}