{
    "Title": "2015 Toyota Camry XLE I4 Automatic",
    "Cash Price": "$10,999",
    "Finance Price": "$147/moEstimate",
    "Finance Details": "$2,500 due at signing \u00b7 72 mo \u00b7 7.39% APR",
    "Exterior": "Gray",
    "Interior": "Unknown",
    "Mileage": "89,866 miles",
    "Fuel Type": "Gas",
    "MPG": "25 city / 35 highway",
    "Transmission": "Automatic Transmission",
    "Drivetrain": "FWD",
    "Engine": "2.5L Inline-4 Gas Inline",
    "Location": "Honolulu, HI",
    "Listed Since": "165 days ago",
    "VIN": "4T1BF1FK7FU476538",
    "Stock Number": "12636",
    "Features": ""
}