{
    "Title": "2018 Tesla Model S 100D",
    "Cash Price": "$27,990",
    "Finance Price": "$442/moEstimate",
    "Finance Details": "$2,799 due at signing \u00b7 72 mo \u00b7 7.99% APR",
    "Exterior": "Gray",
    "Interior": "Black",
    "Mileage": "Laguna Hills, CA (2174 miles away)",
    "Fuel Type": "Electric",
    "MPG": "N/A",
    "Transmission": "Automatic Transmission",
    "Drivetrain": "AWD",
    "Engine": "N/A",
    "Location": "N/A",
    "Listed Since": "Listed 46 days ago",
    "VIN": "5YJSA1E21JF265258",
    "Stock Number": "99241211",
    "Features": "Cruise Control; Backup Camera; Premium Wheels 19+; F&R Parking Sensors; Power Steering; ABS (4-Wheel); Dual AC Electric Motors; All Glass Panoramic Roof; Fog Lights; Electronic Stability Control; Single-Speed Fixed Gear; AWD; Side Air Bags; Power Liftgate Release; Heated Seats; Blind-Spot Alert; AM/FM/HD Radio; Bluetooth Wireless; Dual Power Seats; Knee Air Bags; F&R Head Curtain Air Bags; Dual Air Bags; Power Door Locks; Air Conditioning; Lane Departure Warning; Smart Air Suspension; LED Headlamps; Hill Start Assist; Tilt & Telescoping Wheel; Electronic Traction Control; Alarm System; Daytime Running Lights; Power Windows; Navigation System; See less"
}