{
    "Title": "2024 Chevrolet Silverado 2500HD LT Crew Cab Long Bed 4WD",
    "Cash Price": "$36,000",
    "Finance Price": "$577/moEstimate",
    "Finance Details": "$2,500 due at signing \u00b7 72 mo \u00b7 7.39% APR",
    "Exterior": "Sterling Gray Metallic",
    "Interior": "Jet Black",
    "Mileage": "104,965 miles",
    "Fuel Type": "Gas",
    "MPG": "N/A",
    "Transmission": "Automatic Transmission",
    "Drivetrain": "4WD",
    "Engine": "6.6L V-8 Gas V",
    "Location": "Houston, TX",
    "Listed Since": "9 days ago",
    "VIN": "1GC4YNE74RF160647",
    "Stock Number": "17249",
    "Features": "Durabed, Pickup Bed; Engine, 6.6L V8; Transmission, Allison 10 Speed Automatic; GVWR, 10,650 LBS. (4831 KG); Rear Axle, 3.73 Ratio; LT Preferred Equipment Group; Wheels, 17\" (43.2 CM) Machined Aluminum; Tires, LT245/75r17e All Season, Blackwall; Tire, Spare LT245/75r17e All Season, Blackwall; Seats, Front Bucket; Audio System, Chevrolet Infotainment 3 Premium System; Convenience Package; Remote Start Package; Heat Package; Assist Steps, Chromed, 6\" Rectangular; LED Cargo Area Lighting; Fog Lamps, Front, LED; Chevytec Spray On Bedliner; License Plate Kit, Front; Seating, Heated Driver And Front Outboard Passenger; Seat Adjuster, Driver 10 Way Power; Center Console, Floor Mounted; Steering Wheel, Heated; Remote Vehicle Starter System; Theft Deterrent System, Unauthorized Entry; Wireless Charging; Usb Ports, 2, Charge/Data Ports Located Inside Center Console; Usb Ports, Rear, Dual, Charge Only; Power Outlet, Interior, 120 Volt; Power Outlet, Bed Mounted, 120 Volt; Air Conditioning, Dual Zone Automatic Climate Control; Defogger, Rear Window Electric; See less; Wheel Type; Navigation; Apple CarPlay; Android Auto; Front Heated Seats; See all features"
}