{
    "Title": "2021 Volkswagen Jetta S Automatic",
    "Cash Price": "$10,888",
    "Finance Price": "$145/moEstimate",
    "Finance Details": "$2,500 due at signing \u00b7 72 mo \u00b7 7.39% APR",
    "Exterior": "Pure White",
    "Interior": "Titan Black",
    "Mileage": "79,581 miles",
    "Fuel Type": "Gas",
    "MPG": "29 city / 39 highway",
    "Transmission": "Automatic Transmission",
    "Drivetrain": "FWD",
    "Engine": "1.4L Inline-4 Gas Inline",
    "Location": "Orlando, FL",
    "Listed Since": "9 days ago",
    "VIN": "3VWC57BU0MM061582",
    "Stock Number": "A0563",
    "Features": "Wheel Type; Apple CarPlay; Android Auto; Backup Camera; Bluetooth; Radio: Composition Color w/6.5'' Touchscreen; 4 Speakers; 4-Wheel Disc Brakes; Air Conditioning; Electronic Stability Control; Front Bucket Seats; Front Center Armrest; Tachometer; ABS brakes; AM/FM radio; Alloy wheels; Brake assist; Bumpers: body-color; Delay-off headlights; Driver door bin; Driver vanity mirror; Dual front impact airbags; Dual front side impact airbags; Front anti-roll bar; Front wheel independent suspension; Fully automatic headlights; Illuminated entry; Low tire pressure warning; Occupant sensing airbag; Outside temperature display; Overhead airbag; Overhead console; Panic alarm; Passenger door bin; Passenger vanity mirror; Power door mirrors; Power steering; Power windows; Radio data system; Rear anti-roll bar; Rear reading lights; Rear window defroster; Remote keyless entry; Speed control; Speed-sensing steering; Split folding rear seat; Steering wheel mounted audio controls; Telescoping steering wheel; Tilt steering wheel; Traction control; Trip computer; Variably intermittent wipers; Exterior Parking Camera Rear; Emergency communication system: VW Car-Net services (capabilities require enrollment or subscription); See less"
}