{
    "Title": "2010 Mercedes-Benz ML 350 4MATIC",
    "Cash Price": "$4,695",
    "Finance Price": "Not Available",
    "Finance Details": "Not Available",
    "Exterior": "Gray",
    "Interior": "Black",
    "Mileage": "152,115 miles",
    "Fuel Type": "Gas",
    "MPG": "15 city / 20 highway",
    "Transmission": "Automatic Transmission",
    "Drivetrain": "AWD",
    "Engine": "3.5L V-6 Gas V",
    "Location": "Elizabeth, NJ",
    "Listed Since": "41 days ago",
    "VIN": "4JGBB8GB8AA602001",
    "Stock Number": "602001",
    "Features": "Wheel Type; Moonroof; Power Trunk/Liftgate; Seat Material; Climate Control; Bluetooth; Sunroof/Moonroof; Leather Seats; Bluetooth; Moonroof / Sunroof: one-touch open/close  power glass; remotely operated; Roof rack crossbars: black; Driver seat power adjustments: height  8; Front headrests: adjustable  2; Front seat type: bucket; Passenger seat power adjustments: height  8; Rear headrests: adjustable  3; Rear seat folding: split; Rear seat type: 60-40 split bench; Upholstery: leatherette; ABS: 4-wheel; Braking assist:; Electronic brakeforce distribution:; Front brake type: ventilated disc; Rear brake type: ventilated disc; Daytime running lights:; Exterior entry lights: approach lamps; Front fog lights:; Headlights: auto on/off; Rear fog lights:; Active head restraints: dual front; Child safety door locks:; Child seat anchors:; Impact sensor: post-collision safety system; Airbag deactivation: occupant sensing passenger; Front airbags: dual; Side airbags: front  rear; Side curtain airbags: front  rear; Side mirror adjustments: power; Side mirrors: heated  integrated turn signals; Front wipers: rain sensing  variable intermittent; Heated windshield washer jets:; Liftgate window: fixed; Power windows: remotely operated; Rear privacy glass:; Rear wiper: intermittent; Window defogger: rear; Anti-theft system: alarm  vehicle immobilizer; Power door locks:; Rear seatbelts: center 3-point; Seatbelt force limiters: front  rear; Seatbelt pretensioners: front  rear; 4WD type: full time; Axle ratio: 3.90; Front shock type: gas; Front spring type: coil; Front stabilizer bar:; Front suspension classification: independent; Front suspension type: double wishbone; Rear shock type: gas; Rear spring type: coil; Rear stabilizer bar:; Rear suspension classification: independent; Rear suspension type: multi-link; Satellite communications: TeleAid; Wireless data link: Bluetooth; In-Dash CD: 6 disc  DVD audio; Radio: AM/FM; Speed sensitive volume control:; Spare tire mount location: inside; Spare tire size: temporary; Tire Pressure Monitoring System:; Tire type: all season; Clock:; External temperature display:; Gauge: tachometer; Trip odometer:; Warnings and reminders: coolant temperature warning  lamp failure; low fuel level; low oil pressure; Air filtration: active charcoal; Front air conditioning: automatic climate control; Front air conditioning zones: dual; Armrests: rear center folding with storage; Center console trim: alloy  wood; Floor mat material: carpet; Floor mats: front  rear; Interior accents: wood-tone; Shift knob trim: alloy; Steering wheel trim: leather; Rear trunk/liftgate: liftgate  power operated; Window trim: chrome; Cargo area light:; Cargo cover: retractable; Center console: front console with armrest; Cruise control:; Cupholders: front  rear; Multi-function remote: keyless entry; One-touch windows: 4; Power outlet(s): 12V cargo area  12V front; Power steering:; Reading lights: front  rear; Steering wheel: tilt and telescopic; Steering wheel mounted controls: audio  cruise control; paddle shifter; phone; See less"
}