{
    "Title": "2015 Honda Fit EX Manual",
    "Cash Price": "$7,200",
    "Finance Price": "Not Available",
    "Finance Details": "Not Available",
    "Exterior": "Aegean Blue Metallic",
    "Interior": "Black",
    "Mileage": "Pensacola, FL (459 miles away)",
    "Fuel Type": "Gas",
    "MPG": "29 city / 37 highway",
    "Transmission": "Manual Transmission",
    "Drivetrain": "FWD",
    "Engine": "N/A",
    "Location": "N/A",
    "Listed Since": "Listed 34 days ago",
    "VIN": "3HGGK5G86FM717916",
    "Stock Number": "FM717916",
    "Features": "Wheel Type; Moonroof; Backup Camera; Bluetooth; Driver Air Bag; Passenger Air Bag; Front Head Air Bag; Rear Head Air Bag; A/C; AM/FM Stereo; CD Player; ABS; Front Disc/Rear Drum Brakes; Cruise Control; Rear Defrost; Child Safety Locks; Front Wheel Drive; 4 Cylinder Engine; Floor Mats; Gasoline Fuel; Daytime Running Lights; Keyless Entry; Power Door Locks; Power Mirror(s); Sunroof / Moonroof; Pass-Through Rear Seat; Cloth Seats; Bucket Seats; Power Steering; Adjustable Steering Wheel; Tires - Front Performance; Tires - Rear Performance; Temporary Spare Tire; 6-Speed M/T; Aluminum Wheels; Power Windows; Intermittent Wipers; MP3 Player; Fog Lamps; Steering Wheel Audio Controls; Engine Immobilizer; Automatic Headlights; Driver Vanity Mirror; Passenger Vanity Mirror; Rear Spoiler; Tire Pressure Monitor; Trip Computer; Bluetooth; Back-Up Camera; Stability Control; Brake Assist; Keyless Start; Auxiliary Audio Input; Smart Device Integration; See less"
}