{
    "Title": "2022 Jeep Renegade Latitude 4WD",
    "Cash Price": "$12,000",
    "Finance Price": "$224/moEstimate",
    "Finance Details": "$1,200 due at signing \u00b7 72 mo \u00b7 14.22% APR",
    "Exterior": "Black Clearcoat",
    "Interior": "Black",
    "Mileage": "Alvin, TX (933 miles away)",
    "Fuel Type": "Gas",
    "MPG": "23 city / 29 highway",
    "Transmission": "Automatic Transmission",
    "Drivetrain": "4WD",
    "Engine": "N/A",
    "Location": "N/A",
    "Listed Since": "Listed 68 days ago",
    "VIN": "ZACNJDB17NPN99221",
    "Stock Number": "T23468",
    "Features": "Engine: 1.3L I4 Turbo Mair Di with Ess; Transmission: 9 Speed 948te Automatic; Quick Order Package 22B; Convenience Group; Wheel Type; Navigation; Apple CarPlay; Android Auto; Front Heated Seats; Remote Engine Start; Climate Control; Blind Spot System; Lane Keep Assist; Backup Camera; Parking Sensors; Bluetooth; See less; BLACK CLEARCOAT; ENGINE: 1.3L I4 TURBO MAIR DI W/ESS  (STD); QUICK ORDER PACKAGE 22B  -inc: Engine: 1.3L I4 Turbo MAIR DI w/ESS  Transmission: 9-Speed 948TE Automatic; CONVENIENCE GROUP  -inc: Windshield Wiper De-Icer  115V Auxiliary Power Outlet  Rain Sensitive Windshield Wipers  40/20/40 Rear Seat w/Trunk Pass-Thru  Rear View Auto Dim Mirror  Heated Front Seats  Heated Steering Wheel  Power Adjust 8-Way Driver Seat  Power 2-Way Driver Lumbar Adjust; BLACK  PREMIUM CLOTH BUCKET SEATS; See all features"
}