{
    "Title": "2019 Jaguar I-PACE HSE",
    "Cash Price": "$22,950",
    "Finance Price": "$352/moEstimate",
    "Finance Details": "$2,500 due at signing \u00b7 72 mo \u00b7 7.39% APR",
    "Exterior": "Gray",
    "Interior": "Unknown",
    "Mileage": "41,372 miles",
    "Fuel Type": "Electric",
    "MPG": "N/A",
    "Transmission": "Automatic Transmission",
    "Drivetrain": "AWD",
    "Engine": "N/A",
    "Location": "Raleigh, NC",
    "Listed Since": "11 days ago",
    "VIN": "SADHD2S18K1F60345",
    "Stock Number": "30513P",
    "Features": "9.04 Axle Ratio; 18-Way Heated & Cooled Sport Seats; Windsor Leather Seat Trim; Radio: Meridian 825W Surround Sound System; 4-Wheel Disc Brakes; Air Conditioning; Electronic Stability Control; Front Bucket Seats; Front Center Armrest; Power Liftgate; Spoiler; ABS brakes; Alloy wheels; Audio memory; Auto-dimming door mirrors; Auto-leveling suspension; Automatic temperature control; Brake assist; Bumpers: body-color; Delay-off headlights; Driver door bin; Driver vanity mirror; Dual front impact airbags; Dual front side impact airbags; Four wheel independent suspension; Front anti-roll bar; Front dual zone A/C; Front reading lights; Fully automatic headlights; Garage door transmitter: HomeLink; HVAC memory; Headlight cleaning; Heated door mirrors; Heated front seats; Heated rear seats; Illuminated entry; Low tire pressure warning; Memory seat; Occupant sensing airbag; Outside temperature display; Overhead airbag; Overhead console; Panic alarm; Passenger door bin; Passenger vanity mirror; Power door mirrors; Power driver seat; Power passenger seat; Power steering; Power windows; Radio data system; Rain sensing wipers; Rear anti-roll bar; Rear fog lights; Rear reading lights; Rear seat center armrest; Rear window defroster; Remote keyless entry; Security system; Speed control; Speed-sensing steering; Split folding rear seat; Sport steering wheel; Steering wheel mounted audio controls; Telescoping steering wheel; Tilt steering wheel; Traction control; Trip computer; Turn signal indicator mirrors; Variably intermittent wipers; Ventilated front seats; Auto-dimming Rear-View mirror; 15 Speakers; Compass; AM/FM radio: SiriusXM; Exterior Parking Camera Rear; Auto High-beam Headlights; Navigation system: InControl Navigation Pro; Emergency communication system: InControl Protect; Satellite radio trial duration with new vehicle purchase (months): 3; See less"
}