{
    "Title": "2021 Hyundai Elantra SEL IVT (SULEV)",
    "Cash Price": "$11,498",
    "Finance Price": "$214/moEstimate",
    "Finance Details": "$1,150 due at signing \u00b7 72 mo \u00b7 14.22% APR",
    "Exterior": "Intense Blue",
    "Interior": "Black",
    "Mileage": "Brandon, FL (362 miles away)",
    "Fuel Type": "Gas",
    "MPG": "31 city / 41 highway",
    "Transmission": "Automatic Transmission",
    "Drivetrain": "FWD",
    "Engine": "N/A",
    "Location": "N/A",
    "Listed Since": "Listed 18 days ago",
    "VIN": "5NPLN4AGXMH013218",
    "Stock Number": "H013218",
    "Features": "Convenience + Premium Package; Wheel Locks; Rear Bumper Applique; Carpeted Floor Mats; Cargo Net; Wheel Type; Moonroof; Power Trunk/Liftgate; Premium Audio; Apple CarPlay; Android Auto; Front Heated Seats; Remote Engine Start; Climate Control; Cruise Control; Blind Spot System; Lane Keep Assist; Backup Camera; Bluetooth; See less; INTENSE BLUE; REAR BUMPER APPLIQUE; BLACK  CLOTH SEAT TRIM; CONVENIENCE + PREMIUM PACKAGE  -inc: Option Group 02  Wireless Device Charging  Smart Cruise Control w/Stop & Go  Full 10.25\" LCD TFT Cluster  Heated Front Seats  Electronic Parking Brake  Leather-Wrapped Steering Wheel  leather wrapped shifter  Forward Collision Avoidance Assist  pedestrian  cyclist and junction-turning detection  Heated Outside Mirrors  Option Group 03  Bose Premium Audio  8 speakers  center channel and subwoofer  Wheels: 17\" x 7.0J Alloy  Dark medium gray machine-finished  Tires: 225/45R17  LED & Bulb Tail Lights  Side Mirror Turn Signal Indicators  Passenger Seat Back Pocket  Dark Chrome Exterior Accents  dark chrome grille  lower bumper and emblem  Chrome DLO  Chrome window belt moldings  Power Driver Seat w/Lumbar  Power Sunroof  tilt and slide and safety one-touch  60/40 Split-Folding Rear Seat  armrest and cupholder  Hyundai Digital Key; CARGO NET; See all features"
}