{
    "Title": "2013 Ford F-150 Limited SuperCrew 5.5' Box 4WD",
    "Cash Price": "$19,140",
    "Finance Price": "Not Available",
    "Finance Details": "Not Available",
    "Exterior": "White Platinum Metallic Tri-Coat",
    "Interior": "Red/Black",
    "Mileage": "Austin, TX (1062 miles away)",
    "Fuel Type": "Gas",
    "MPG": "14 city / 19 highway",
    "Transmission": "Automatic Transmission",
    "Drivetrain": "4WD",
    "Engine": "3.5L V-6 Gas V",
    "Location": "N/A",
    "Listed Since": "Listed 3 days ago",
    "VIN": "1FTFW1ET3DFC11813",
    "Stock Number": "DFC11813P",
    "Features": "Wheel Type; Moonroof; Premium Audio; Navigation; Seat Material; Front Heated Seats; Front Cooled Seats; Remote Engine Start; Climate Control; Backup Camera; Parking Sensors; Bluetooth; Tow Hitch; See less; Driver Air Bag; Passenger Air Bag; Front Side Air Bag; Front Head Air Bag; Rear Head Air Bag; See all features"
}