{
    "Title": "2014 INFINITI QX70 V6 AWD",
    "Cash Price": "$9,500",
    "Finance Price": "Not Available",
    "Finance Details": "Not Available",
    "Exterior": "Black Obsidian",
    "Interior": "Graphite",
    "Mileage": "100,183 miles",
    "Fuel Type": "Gas",
    "MPG": "16 city / 22 highway",
    "Transmission": "Automatic Transmission",
    "Drivetrain": "AWD",
    "Engine": "3.7L V-6 Gas V",
    "Location": "Houston, TX",
    "Listed Since": "57 days ago",
    "VIN": "JN8CS1MW8EM411906",
    "Stock Number": "411906",
    "Features": "Graphite, Leather Appointed Seat Trim; Wheel Type; Moonroof; Power Trunk/Liftgate; Premium Audio; Navigation; Seat Material; Front Heated Seats; Front Cooled Seats; Climate Control; Backup Camera; Parking Sensors; Bluetooth; See less"
}