{
    "Title": "2017 Chevrolet Trax LS FWD",
    "Cash Price": "$6,898",
    "Finance Price": "$129/moEstimate",
    "Finance Details": "$690 due at signing \u00b7 72 mo \u00b7 14.22% APR",
    "Exterior": "Summit White",
    "Interior": "Jet Black/Light Ash Gray",
    "Mileage": "Corinth, MS (1702 miles away)",
    "Fuel Type": "Gas",
    "MPG": "25 city / 33 highway",
    "Transmission": "Automatic Transmission",
    "Drivetrain": "FWD",
    "Engine": "N/A",
    "Location": "N/A",
    "Listed Since": "Listed 15 days ago",
    "VIN": "3GNCJKSB3HL263495",
    "Stock Number": "16329",
    "Features": "Engine, Ecotec Turbo 1.4L Variable Valve Timing Dohc 4 Cylinder Sequential Mfi; Transmission, 6 Speed Automatic; Axle, 3.53 Final Drive Ratio; LS Preferred Equipment Group; Seats, Front Bucket With Driver Power Lumbar; Jet Black/Light Ash Gray, Cloth Seat Trim; Audio System, Chevrolet Mylink Radio; See less; Apple CarPlay; Android Auto; Backup Camera; Bluetooth; Knee Air Bags; Automatic 6-Spd; Keyless Entry; F&R Head Curtain Air Bags; Tilt & Telescoping Wheel; See all features"
}