{
    "Title": "2022 Honda CR-V EX AWD",
    "Cash Price": "$21,697",
    "Finance Price": "$331/moEstimate",
    "Finance Details": "$2,500 due at signing \u00b7 72 mo \u00b7 7.39% APR",
    "Exterior": "Platinum White Pearl",
    "Interior": "Black",
    "Mileage": "27,153 miles",
    "Fuel Type": "Gas",
    "MPG": "27 city / 32 highway",
    "Transmission": "Automatic Transmission",
    "Drivetrain": "AWD",
    "Engine": "1.5L Inline-4 Gas Inline",
    "Location": "Islip, NY",
    "Listed Since": "16 days ago",
    "VIN": "2HKRW2H58NH631428",
    "Stock Number": "W782",
    "Features": "Wheel Type; Moonroof; Apple CarPlay; Android Auto; Front Heated Seats; Remote Engine Start; Climate Control; Cruise Control; Blind Spot System; Lane Keep Assist; Backup Camera; Bluetooth; See less; 6 Speakers; AM/FM radio: SiriusXM; Radio data system; Radio: 180-Watt AM/FM/HD/SiriusXM Audio System; Air Conditioning; See all features"
}