{
    "Title": "2021 Ferrari SF90 Coupe",
    "Cash Price": "$449,900",
    "Finance Price": "$8,391/moEstimate",
    "Finance Details": "$44,990 due at signing \u00b7 72 mo \u00b7 14.22% APR",
    "Exterior": "Grigio Scuro",
    "Interior": "Nero",
    "Mileage": "Los Angeles, CA (9 miles away)",
    "Fuel Type": "Hybrid",
    "MPG": "N/A",
    "Transmission": "Automatic Transmission",
    "Drivetrain": "AWD",
    "Engine": "4.0L V-8 Hybrid V",
    "Location": "N/A",
    "Listed Since": "Listed 45 days ago",
    "VIN": "ZFF95NLA3M0264301",
    "Stock Number": "C2039",
    "Features": "Wheel Type; Navigation; Apple CarPlay; Seat Material; Climate Control; Backup Camera; Parking Sensors; Bluetooth; See less; Entertainment; System"
}