{
    "Title": "2017 Ram 1500 SLT Crew Cab 5'7\" Box 4WD",
    "Cash Price": "$12,500",
    "Finance Price": "Not Available",
    "Finance Details": "Not Available",
    "Exterior": "Bright White Clearcoat",
    "Interior": "Diesel Gray/Black",
    "Mileage": "151,037 miles",
    "Fuel Type": "Gas",
    "MPG": "16 city / 23 highway",
    "Transmission": "Automatic Transmission",
    "Drivetrain": "4WD",
    "Engine": "3.6L V-6 Gas V",
    "Location": "Union City, GA",
    "Listed Since": "62 days ago",
    "VIN": "1C6RR7LG1HS568053",
    "Stock Number": "568053",
    "Features": "Engine: 3.6L V6 24V VVT; Transmission: 8 Speed Automatic (845re); Quick Order Package 22G SLT; 3.21 Rear Axle Ratio; 17\" X 7\" Aluminum Wheels; Tires: P265/70R17 BSW As; GVWR: 6,800 LBS; Radio: Uconnect 3C with 8.4\" Display; Tri Fold Tonneau Cover; Parkview Rear Back Up Camera; See less; Wheel Type; Navigation; Remote Engine Start; Climate Control; Backup Camera; See all features; Engine: 3.6L V6 24V VVT -inc: Flex fuel capable; 3.21 Rear Axle Ratio; GVWR: 6-800 lbs; 50 State Emissions; Transmission w/Driver Selectable Mode and Oil Cooler; See all features"
}