{
    "Title": "2023 Ford Bronco Raptor 4 Door Advanced 4x4",
    "Cash Price": "$72,940",
    "Finance Price": "$1,103/moEstimate",
    "Finance Details": "$7,294 due at signing \u00b7 72 mo \u00b7 6.49% APR",
    "Exterior": "Iconic Silver Metallic",
    "Interior": "Unknown",
    "Mileage": "Seattle, WA (967 miles away)",
    "Fuel Type": "Gas",
    "MPG": "15 city / 16 highway",
    "Transmission": "Automatic Transmission",
    "Drivetrain": "4WD",
    "Engine": "3.0L V-6 Gas V",
    "Location": "N/A",
    "Listed Since": "Listed 17 days ago",
    "VIN": "1FMEE5JR9PLB36133",
    "Stock Number": "U33315A",
    "Features": "17\" Dark Carbonized Gray Alloy Painted Wheels; Blue with Black Onyx, Leather Trimmed/Vinyl Bucket Seats with Blue/Black; Keyless Entry Keypad; Equipment Group 374A Lux Package; Wheel Type; Premium Audio; Navigation; Apple CarPlay; Android Auto; Seat Material; Front Heated Seats; Remote Engine Start; Climate Control; Cruise Control; Blind Spot System; Lane Keep Assist; Backup Camera; Parking Sensors; Bluetooth; See less; Navigation system: Connected Navigation; Equipment Group 374A Lux Package; Lux Package; Convertible HardTop; 10 Speakers w/Subwoofer; See all features"
}