{
    "Title": "2023 Volvo XC40 Recharge Plus",
    "Cash Price": "$30,991",
    "Finance Price": "$567/moEstimate",
    "Finance Details": "$2,500 due at signing \u00b7 60 mo \u00b7 7.19% APR",
    "Exterior": "Crystal White Metallic",
    "Interior": "Charcoal",
    "Mileage": "10,117 miles",
    "Fuel Type": "Electric",
    "MPG": "N/A",
    "Transmission": "Automatic Transmission",
    "Drivetrain": "AWD",
    "Engine": "N/A",
    "Location": "Marietta, GA",
    "Listed Since": "26 days ago",
    "VIN": "YV4ED3ULXP2019926",
    "Stock Number": "NAC240742A",
    "Features": "Wheel Type; Moonroof; Power Trunk/Liftgate; Navigation; Apple CarPlay; Android Auto; Seat Material; Front Heated Seats; Remote Engine Start; Climate Control; Blind Spot System; Lane Keep Assist; Backup Camera; Parking Sensors; Bluetooth; See less; Navigation system: Sensus Navigation Pro; Internet access capable: Digital Services Package w/ 4 Year Subscription; 8 Speakers; Audio memory; Radio data system; See all features"
}