{
    "Title": "2017 Ford Focus SE Hatchback",
    "Cash Price": "$7,550",
    "Finance Price": "$87/moEstimate",
    "Finance Details": "$2,500 due at signing \u00b7 72 mo \u00b7 7.39% APR",
    "Exterior": "Magnetic Metallic",
    "Interior": "Charcoal Black",
    "Mileage": "75,172 miles",
    "Fuel Type": "Gas",
    "MPG": "26 city / 38 highway",
    "Transmission": "Manual Transmission",
    "Drivetrain": "FWD",
    "Engine": "2.0L Inline-4 Gas Inline",
    "Location": "Addison, TX",
    "Listed Since": "10 days ago",
    "VIN": "1FADP3K21HL341355",
    "Stock Number": "341355A",
    "Features": "Equipment Group 200A; Wheel Type; Backup Camera; Bluetooth; Equipment Group 200A; 16'' Painted Aluminum Wheels; Cloth Front Bucket Seats; Radio: AM/FM Single-CD/MP3-Capable; SYNC Communications & Entertainment System; 6 Speakers; Air Conditioning; Electronic Stability Control; Front Bucket Seats; Front Center Armrest; Spoiler; Tachometer; ABS brakes; Adjustable head restraints: driver and passenger w/tilt; Alloy wheels; Brake assist; Bumpers: body-color; CD player; Delay-off headlights; Driver door bin; Driver vanity mirror; Dual front impact airbags; Dual front side impact airbags; Four wheel independent suspension; Front anti-roll bar; Front reading lights; Fully automatic headlights; Illuminated entry; Knee airbag; Low tire pressure warning; Occupant sensing airbag; Outside temperature display; Overhead airbag; Overhead console; Panic alarm; Passenger door bin; Passenger vanity mirror; Power door mirrors; Power steering; Power windows; Radio data system; Rear anti-roll bar; Rear window defroster; Rear window wiper; Remote keyless entry; Speed control; Split folding rear seat; Steering wheel mounted audio controls; Telescoping steering wheel; Tilt steering wheel; Traction control; Trip computer; Turn signal indicator mirrors; Variably intermittent wipers; Compass; AM/FM radio: SiriusXM; Exterior Parking Camera Rear; Emergency communication system: 911 Assist; See less"
}